tweetopic/__init__.py
tweetopic/_btm.py
tweetopic/_dmm.py
tweetopic/_doc.py
tweetopic/_prob.py
tweetopic/btm.py
tweetopic/dmm.py
tweetopic/exceptions.py
tweetopic/func.py
tweetopic/utils.py
tweetopic-0.4.0.dist-info/LICENSE
tweetopic-0.4.0.dist-info/METADATA
tweetopic-0.4.0.dist-info/WHEEL
tweetopic-0.4.0.dist-info/RECORD
