Metadata-Version: 2.1
Name: tweetopic
Version: 0.4.0
Summary: Topic modelling over short texts
License: MIT
Author: Márton Kardos
Author-email: power.up1163@gmail.com
Requires-Python: >=3.8.0
Classifier: License :: OSI Approved :: MIT License
Classifier: Programming Language :: Python :: 3
Classifier: Programming Language :: Python :: 3.8
Classifier: Programming Language :: Python :: 3.9
Classifier: Programming Language :: Python :: 3.10
Classifier: Programming Language :: Python :: 3.11
Classifier: Programming Language :: Python :: 3.12
Requires-Dist: deprecated (>=1.2.0)
Requires-Dist: joblib (>=1.1.0)
Requires-Dist: numba (>=0.58.1)
Requires-Dist: numpy (>=1.22,<1.27.0)
Requires-Dist: scikit-learn (>=1.1.1,<1.4.0)
Requires-Dist: tqdm (>=4.64.0)
